whisper_s2t/__init__.py
whisper_s2t/audio.py
whisper_s2t/configs.py
whisper_s2t/data.py
whisper_s2t/utils.py
whisper_s2t/assets/frame_vad_model_cpu.ts
whisper_s2t/assets/frame_vad_model_gpu.ts
whisper_s2t/assets/lang_codes.txt
whisper_s2t/assets/mel_filters.npz
whisper_s2t/assets/seg_vad_model_cpu.ts
whisper_s2t/assets/seg_vad_model_gpu.ts
whisper_s2t/assets/silent.mp3
whisper_s2t/assets/vad_pp_cpu.ts
whisper_s2t/assets/vad_pp_gpu.ts
whisper_s2t/backends/__init__.py
whisper_s2t/backends/ctranslate2/__init__.py
whisper_s2t/backends/ctranslate2/hf_utils.py
whisper_s2t/backends/ctranslate2/model.py
whisper_s2t/backends/ctranslate2/tokenizer.py
whisper_s2t/backends/huggingface/__init__.py
whisper_s2t/backends/huggingface/model.py
whisper_s2t/backends/openai/__init__.py
whisper_s2t/backends/openai/model.py
whisper_s2t/backends/tensorrt/__init__.py
whisper_s2t/backends/tensorrt/hf_utils.py
whisper_s2t/backends/tensorrt/model.py
whisper_s2t/backends/tensorrt/tokenizer.py
whisper_s2t/backends/tensorrt/trt_model.py
whisper_s2t/backends/tensorrt/engine_builder/__init__.py
whisper_s2t/backends/tensorrt/engine_builder/builder.py
whisper_s2t/backends/tensorrt/engine_builder/download_utils.py
whisper_s2t/backends/tensorrt/engine_builder/model_utils.py
whisper_s2t/speech_segmenter/__init__.py
whisper_s2t/speech_segmenter/frame_vad.py
whisper_s2t/speech_segmenter/seg_vad.py
whisper_s2t-1.3.1.dist-info/LICENSE
whisper_s2t-1.3.1.dist-info/METADATA
whisper_s2t-1.3.1.dist-info/WHEEL
whisper_s2t-1.3.1.dist-info/top_level.txt
whisper_s2t-1.3.1.dist-info/RECORD
