Metadata-Version: 2.1
Name: whisper-s2t
Version: 1.3.1
Summary: An Optimized Speech-to-Text Pipeline for the Whisper Model.
Home-page: https://github.com/shashikg/WhisperS2T
Author: Shashi Kant Gupta
License: MIT
Requires-Python: >=3.8
License-File: LICENSE
Requires-Dist: tqdm
Requires-Dist: rich
Requires-Dist: torch
Requires-Dist: numpy
Requires-Dist: platformdirs
Requires-Dist: ctranslate2
Requires-Dist: tokenizers
Requires-Dist: huggingface-hub
Requires-Dist: accelerate
Requires-Dist: optimum
Requires-Dist: transformers
Requires-Dist: openai-whisper
Requires-Dist: nvidia-ml-py
